{
  "collapse-filter": true,
  "search": "",
  "showTags": false,
  "showAttachments": false,
  "hideUnresolved": false,
  "showOrphans": true,
  "collapse-color-groups": true,
  "colorGroups": [],
  "collapse-display": false,
  "showArrow": false,
  "textFadeMultiplier": -1.6,
  "nodeSizeMultiplier": 1.89802494802495,
  "lineSizeMultiplier": 1.53128898128898,
  "collapse-forces": false,
  "centerStrength": 0.138253638253638,
  "repelStrength": 9.91683991683992,
  "linkStrength": 0.408523908523909,
  "linkDistance": 451,
  "scale": 0.047895926345894964,
  "close": false
}